[
  {
    "Event_ID": "VPqVn16",
    "Sources": "https://en.wikipedia.org/wiki/1972%E2%80%9373_Australian_region_cyclone_season",
    "Event_Names": "1972\u201373 Australian region cyclone season",
    "Total_Summary_Affected": {
      "Total_Affected": "NULL",
      "Total_Affected_Annotation": "Info_Box"
    },
    "Instance_Per_Administrative_Areas_Affected": [
      {
        "Administrative_Areas": [
          "Australia"
        ],
        "Start_Date": "7 December 1972",
        "End_Date": "6 May 1973",
        "Num": "NULL",
        "Annotation": "Info_Box"
      }
    ],
    "Specific_Instance_Per_Administrative_Area_Affected": [
      {
        "Administrative_Area": "Australia",
        "Locations": [
          "Flores"
        ],
        "Start_Date": "26 April 1973",
        "End_Date": "29 April 1973",
        "Num": "53",
        "Annotation": "Severe Tropical Cyclone Thirteen"
      },
      {
        "Administrative_Area": "Australia",
        "Locations": [
          "Timor Sea"
        ],
        "Start_Date": "26 April 1973",
        "End_Date": "29 April 1973",
        "Num": "21",
        "Annotation": "Severe Tropical Cyclone Thirteen"
      },
      {
        "Administrative_Area": "Australia",
        "Locations": [
          "Flores"
        ],
        "Start_Date": "26 April 1973",
        "End_Date": "29 April 1973",
        "Num": "over 1,500",
        "Annotation": "Severe Tropical Cyclone Thirteen"
      }
    ],
    "Total_Summary_Buildings_Damaged": {
      "Total_Buildings_Damaged": "NULL",
      "Total_Buildings_Damaged_Annotation": "Info_Box"
    },
    "Instance_Per_Administrative_Areas_Buildings_Damaged": [
      {
        "Administrative_Areas": [
          "Australia"
        ],
        "Start_Date": "21 January 1973",
        "End_Date": "21 January 1973",
        "Num": "more than 30 houses",
        "Annotation": "Severe Tropical Cyclone Kerry"
      },
      {
        "Administrative_Areas": [
          "Indonesia"
        ],
        "Start_Date": "26 April 1973",
        "End_Date": "29 April 1973",
        "Num": "Widespread destruction of houses, schools, and bridges",
        "Annotation": "Severe Tropical Cyclone Thirteen"
      }
    ],
    "Specific_Instance_Per_Administrative_Area_Buildings_Damaged": [
      {
        "Administrative_Area": "Australia",
        "Locations": [
          "Wickham"
        ],
        "Start_Date": "21 January 1973",
        "End_Date": "21 January 1973",
        "Num": "more than 30 houses",
        "Annotation": "Severe Tropical Cyclone Kerry"
      },
      {
        "Administrative_Area": "Indonesia",
        "Locations": [
          "Flores"
        ],
        "Start_Date": "26 April 1973",
        "End_Date": "29 April 1973",
        "Num": "Widespread destruction of houses, schools, and bridges",
        "Annotation": "Severe Tropical Cyclone Thirteen"
      }
    ],
    "Total_Summary_Deaths": {
      "Total_Deaths": "1,650+",
      "Total_Deaths_Annotation": "Info_Box"
    },
    "Instance_Per_Administrative_Areas_Deaths": [
      {
        "Administrative_Areas": [
          "Australia"
        ],
        "Start_Date": "7 December 1972",
        "End_Date": "6 May 1973",
        "Num": "NULL",
        "Annotation": "Info_Box"
      }
    ],
    "Specific_Instance_Per_Administrative_Area_Deaths": [
      {
        "Administrative_Area": "Australia",
        "Locations": [
          "Flores"
        ],
        "Start_Date": "26 April 1973",
        "End_Date": "29 April 1973",
        "Num": "53",
        "Annotation": "Severe Tropical Cyclone Thirteen"
      },
      {
        "Administrative_Area": "Australia",
        "Locations": [
          "Timor Sea"
        ],
        "Start_Date": "26 April 1973",
        "End_Date": "29 April 1973",
        "Num": "21",
        "Annotation": "Severe Tropical Cyclone Thirteen"
      },
      {
        "Administrative_Area": "Australia",
        "Locations": [
          "Flores"
        ],
        "Start_Date": "26 April 1973",
        "End_Date": "29 April 1973",
        "Num": "over 1,500",
        "Annotation": "Severe Tropical Cyclone Thirteen"
      }
    ],
    "Total_Summary_Displaced": {
      "Total_Displaced": "NULL",
      "Total_Displaced_Annotation": "Info_Box"
    },
    "Instance_Per_Administrative_Areas_Displaced": [
      {
        "Administrative_Areas": [
          "Australia"
        ],
        "Start_Date": "21 January 1973",
        "End_Date": "21 January 1973",
        "Num": "NULL",
        "Annotation": "Severe Tropical Cyclone Kerry"
      }
    ],
    "Specific_Instance_Per_Administrative_Area_Displaced": [
      {
        "Administrative_Area": "Australia",
        "Locations": [
          "Wickham"
        ],
        "Start_Date": "21 January 1973",
        "End_Date": "21 January 1973",
        "Num": "NULL",
        "Annotation": "Severe Tropical Cyclone Kerry"
      }
    ],
    "Total_Summary_Homeless": {
      "Total_Homeless": "NULL",
      "Total_Homeless_Annotation": "NULL"
    },
    "Instance_Per_Administrative_Areas_Homeless": [
      {
        "Administrative_Areas": [
          "Australia"
        ],
        "Start_Date": "21 January 1973",
        "End_Date": "21 January 1973",
        "Num": "more than 30 houses were partly unroofed and some houses received major damage",
        "Annotation": "Severe Tropical Cyclone Kerry"
      }
    ],
    "Specific_Instance_Per_Administrative_Area_Homeless": [
      {
        "Administrative_Area": "Australia",
        "Locations": [
          "Wickham"
        ],
        "Start_Date": "21 January 1973",
        "End_Date": "21 January 1973",
        "Num": "more than 30 houses were partly unroofed and some houses received major damage",
        "Annotation": "Severe Tropical Cyclone Kerry"
      },
      {
        "Administrative_Area": "Indonesia",
        "Locations": [
          "Flores"
        ],
        "Start_Date": "26 April 1973",
        "End_Date": "29 April 1973",
        "Num": "Widespread destruction of houses, schools, and bridges was reported in four of the island's districts",
        "Annotation": "Severe Tropical Cyclone Thirteen"
      }
    ],
    "Total_Summary_Injuries": {
      "Total_Injuries": "NULL",
      "Total_Injuries_Annotation": "Info_Box"
    },
    "Instance_Per_Administrative_Areas_Injuries": [
      {
        "Administrative_Areas": [
          "Australia"
        ],
        "Start_Date": "21 January 1973",
        "End_Date": "21 January 1973",
        "Num": "NULL",
        "Annotation": "Severe Tropical Cyclone Kerry"
      }
    ],
    "Specific_Instance_Per_Administrative_Area_Injuries": [
      {
        "Administrative_Area": "Australia",
        "Locations": [
          "Wickham"
        ],
        "Start_Date": "21 January 1973",
        "End_Date": "21 January 1973",
        "Num": "NULL",
        "Annotation": "Severe Tropical Cyclone Kerry"
      }
    ],
    "Total_Summary_Insured_Damage": {
      "Total_Insured_Damage": "NULL",
      "Total_Insured_Damage_Unit": "NULL",
      "Total_Insured_Damage_Inflation_Adjusted": "NULL",
      "Total_Insured_Damage_Inflation_Adjusted_Year": "NULL",
      "Total_Insured_Damage_Annotation": "NULL"
    },
    "Instance_Per_Administrative_Areas_Insured_Damage": [
      {
        "Administrative_Areas": [
          "Australia"
        ],
        "Start_Date": "7 December 1972",
        "End_Date": "6 May 1973",
        "Num": "NULL",
        "Num_Unit": "NULL",
        "Num_Inflation_Adjusted": "NULL",
        "Num_Inflation_Adjusted_Year": "NULL",
        "Annotation": "Info_Box"
      }
    ],
    "Specific_Instance_Per_Administrative_Area_Insured_Damage": [
      {
        "Administrative_Area": "Australia",
        "Locations": [
          "Wickham"
        ],
        "Start_Date": "21 January 1973",
        "End_Date": "21 January 1973",
        "Num": "NULL",
        "Num_Unit": "NULL",
        "Num_Inflation_Adjusted": "NULL",
        "Num_Inflation_Adjusted_Year": "NULL",
        "Annotation": "Severe Tropical Cyclone Kerry"
      }
    ],
    "Total_Summary_Damage": {
      "Total_Damage": "Unknown",
      "Total_Damage_Unit": "NULL",
      "Total_Damage_Inflation_Adjusted": "NULL",
      "Total_Damage_Inflation_Adjusted_Year": "NULL",
      "Total_Damage_Annotation": "Info_Box"
    },
    "Instance_Per_Administrative_Areas_Damage": [
      {
        "Administrative_Areas": [
          "Australia"
        ],
        "Start_Date": "7 December 1972",
        "End_Date": "6 May 1973",
        "Num": "NULL",
        "Num_Unit": "NULL",
        "Num_Inflation_Adjusted": "NULL",
        "Num_Inflation_Adjusted_Year": "NULL",
        "Annotation": "1972\u201373 Australian region cyclone season"
      }
    ],
    "Specific_Instance_Per_Administrative_Area_Damage": [
      {
        "Administrative_Area": "Australia",
        "Locations": [
          "Wickham"
        ],
        "Start_Date": "21 January 1973",
        "End_Date": "21 January 1973",
        "Num": "over one million dollars",
        "Num_Unit": "USD",
        "Num_Inflation_Adjusted": "No",
        "Num_Inflation_Adjusted_Year": "NULL",
        "Annotation": "Severe Tropical Cyclone Kerry"
      }
    ],
    "Main_Event": "Tropical Storm/Cyclone",
    "Main_Event_Annotation": "Info_Box",
    "Hazards": "Wind|Flood",
    "Hazards_Annotation": "Info_Box|Severe Tropical Cyclone Thirteen",
    "Start_Date": "7 December 1972",
    "End_Date": "6 May 1973",
    "Time_Annotation": "Info_Box"
  }
]
